pyconvertapi_image_converter/__init__.py
pyconvertapi_image_converter/image_converter.py
pyconvertapi_image_converter-0.1.3.dist-info/LICENSE.md
pyconvertapi_image_converter-0.1.3.dist-info/METADATA
pyconvertapi_image_converter-0.1.3.dist-info/WHEEL
pyconvertapi_image_converter-0.1.3.dist-info/top_level.txt
pyconvertapi_image_converter-0.1.3.dist-info/RECORD
