Metadata-Version: 2.1
Name: pyconvertapi-image-converter
Version: 0.1.3
Summary: PyConvertAPI Image Converter is a Python library for converting images to different formats using ConvertAPI
Author-email: ti-oluwa <tioluwa.dev@gmail.com>
Maintainer-email: ti-oluwa <tioluwa.dev@gmail.com>
Project-URL: Homepage, https://github.com/ti-oluwa/pyconvertapi_image_converter
Project-URL: Bug Tracker, https://github.com/ti-oluwa/pyconvertapi_image_converter/issues
Project-URL: Repository, https://github.com/ti-oluwa/pyconvertapi_image_converter
Keywords: Image format conversion,ConvertAPI
Classifier: Programming Language :: Python :: 3
Classifier: License :: OSI Approved :: MIT License
Classifier: Operating System :: OS Independent
Classifier: Environment :: Console
Requires-Python: >=3.7
License-File: LICENSE.md
Requires-Dist: convertapi
